pyreactlab_core/__init__.py
pyreactlab_core/app.py
pyreactlab_core/configs/__init__.py
pyreactlab_core/configs/constants.py
pyreactlab_core/configs/info.py
pyreactlab_core/core/__init__.py
pyreactlab_core/core/chem_react.py
pyreactlab_core/docs/__init__.py
pyreactlab_core/docs/chem_balance.py
pyreactlab_core/docs/chem_utils.py
pyreactlab_core/models/__init__.py
pyreactlab_core/models/reaction.py
pyreactlab_core/utils/__init__.py
pyreactlab_core/utils/tools.py
pyreactlab_core-0.1.3.dist-info/licenses/LICENSE
pyreactlab_core-0.1.3.dist-info/METADATA
pyreactlab_core-0.1.3.dist-info/WHEEL
pyreactlab_core-0.1.3.dist-info/top_level.txt
pyreactlab_core-0.1.3.dist-info/RECORD
