Metadata-Version: 2.4
Name: pyreactlab-core
Version: 0.1.3
Summary: pyreactlab-core is the core foundation of the PyReactLab ecosystem, offering shared data structures and algorithms for chemical reaction representation, stoichiometry, and reaction analysis.
Author-email: Sina Gilassi <sina.gilassi@gmail.com>
License-Expression: Apache-2.0
Project-URL: Homepage, https://github.com/sinagilassi/PyReactLab-Core
Project-URL: Documentation, https://pyreactlab-core.readthedocs.io/en/latest/
Project-URL: Source, https://github.com/sinagilassi/PyReactLab-Core
Project-URL: Tracker, https://github.com/sinagilassi/PyReactLab-Core/issues
Keywords: chemical-engineering,chemical-reactions,reaction-representation,reaction-stoichiometry,reaction-analysis
Classifier: Development Status :: 1 - Planning
Classifier: Intended Audience :: Education
Classifier: Programming Language :: Python :: 3.11
Classifier: Operating System :: Unix
Classifier: Operating System :: MacOS :: MacOS X
Classifier: Operating System :: Microsoft :: Windows
Requires-Python: >=3.11
License-File: LICENSE
Requires-Dist: numpy>=2.4.0
Requires-Dist: scipy>=1.16.3
Requires-Dist: pydantic>=2.12.5
Requires-Dist: pydantic-settings>=2.12.0
Requires-Dist: rich>=14.2.0
Requires-Dist: pythermodb-settings
Dynamic: license-file
